poke/__init__.py
iflow_mcp_sachin_crypto_pokemon-0.1.2.dist-info/METADATA
iflow_mcp_sachin_crypto_pokemon-0.1.2.dist-info/WHEEL
iflow_mcp_sachin_crypto_pokemon-0.1.2.dist-info/entry_points.txt
iflow_mcp_sachin_crypto_pokemon-0.1.2.dist-info/RECORD
