Metadata-Version: 2.4
Name: iflow-mcp_sachin-crypto_pokemon
Version: 0.1.2
Summary: Add your description here
Requires-Python: >=3.13
Requires-Dist: httpx>=0.27.0
Requires-Dist: mcp[cli]>=1.6.0
